ringr/__init__.py
ringr/__main__.py
ringr/audio.py
ringr/config.py
ringr/config_parser.py
ringr/exceptions.py
ringr/notifiers/__init__.py
ringr/notifiers/ha_notifier.py
ringr/notifiers/notifier.py
ringr/notifiers/telegram_notifier.py
ringr-0.1.6.dist-info/LICENSE
ringr-0.1.6.dist-info/METADATA
ringr-0.1.6.dist-info/WHEEL
ringr-0.1.6.dist-info/entry_points.txt
ringr-0.1.6.dist-info/top_level.txt
ringr-0.1.6.dist-info/RECORD
