Metadata-Version: 2.2
Name: ringr
Version: 0.1.6
Summary: Sound event detection system
Author-email: Alberto Alcolea <albertoalcolea@gmail.com>
License: GNU General Public License v3 (GPLv3)
Project-URL: source, https://github.com/albertoalcolea/ringr
Project-URL: changelog, https://github.com/albertoalcolea/ringr/releases
Project-URL: issues, https://github.com/albertoalcolea/ringr/issues
Project-URL: documentation, https://albertoalcolea.com/blog/ringr-a-sound-event-detection-system/
Keywords: ringr,ring,sound,sound detection,audio,audio detection,frequency analyzer,peak detection,home assistant
Classifier: Development Status :: 4 - Beta
Classifier: Environment :: Console
Classifier: Intended Audience :: End Users/Desktop
Classifier: License :: OSI Approved :: GNU General Public License v3 (GPLv3)
Classifier: Operating System :: OS Independent
Classifier: Programming Language :: Python
Classifier: Programming Language :: Python :: 3
Classifier: Programming Language :: Python :: 3.9
Classifier: Programming Language :: Python :: 3.10
Classifier: Programming Language :: Python :: 3.11
Classifier: Programming Language :: Python :: 3.12
Classifier: Programming Language :: Python :: 3 :: Only
Classifier: Programming Language :: Python :: Implementation :: CPython
Classifier: Topic :: Multimedia :: Sound/Audio :: Analysis
Requires-Python: >=3.9
License-File: LICENSE
Requires-Dist: sounddevice==0.4.6
Requires-Dist: numpy==1.26.2
Requires-Dist: paho-mqtt==1.6.1
Provides-Extra: dev
Requires-Dist: flake8>=4.0.1; extra == "dev"
Requires-Dist: build>=1.2.2.post1; extra == "dev"
Requires-Dist: twine>=4.0.0; extra == "dev"
